{
  "user_id": 201,
  "nickname": "유진",
  "habit_id": 2,
  "name": "평일 오전 운동",
  "day_of_week": [1, 2, 3, 4, 5],
  "start_time": "07:00",
  "end_time": "08:00",
  "habit_log": [
    {
      "date": "2025-08-01",
      "completed": true
    },
    {
      "date": "2025-08-04",
      "completed": true
    },
    {
      "date": "2025-08-05",
      "completed": true
    },
    {
      "date": "2025-08-06",
      "completed": false,
      "failure_reason": ["날씨 더움", "컨디션 저하"]
    },
    {
      "date": "2025-08-07",
      "completed": false,
      "failure_reason": ["의욕 저하"]
    },
    {
      "date": "2025-08-08",
      "completed": true
    },
    {
      "date": "2025-08-11",
      "completed": false,
      "failure_reason": ["근육통"]
    },
    {
      "date": "2025-08-12",
      "completed": false,
      "failure_reason": ["알람 못 들음", "수면 부족"]
    },
    {
      "date": "2025-08-13",
      "completed": false,
      "failure_reason": ["날씨 더움"]
    },
    {
      "date": "2025-08-14",
      "completed": true
    },
    {
      "date": "2025-08-15",
      "completed": false,
      "failure_reason": ["외출 일정"]
    },
    {
      "date": "2025-08-18",
      "completed": true
    },
    {
      "date": "2025-08-19",
      "completed": false,
      "failure_reason": ["날씨 더움", "수면 부족"]
    },
    {
      "date": "2025-08-20",
      "completed": true
    },
    {
      "date": "2025-08-21",
      "completed": false,
      "failure_reason": ["근육통", "의욕 저하"]
    },
    {
      "date": "2025-08-22",
      "completed": true
    },
    {
      "date": "2025-08-25",
      "completed": true
    },
    {
      "date": "2025-08-26",
      "completed": false,
      "failure_reason": ["수면 부족", "컨디션 저하"]
    },
    {
      "date": "2025-08-27",
      "completed": true
    },
    {
      "date": "2025-08-28",
      "completed": true
    },
    {
      "date": "2025-08-29",
      "completed": false,
      "failure_reason": ["의욕 저하", "외출 일정"]
    }
  ]
}